{
	"configurations" : 
	[
		{
			"directories" : 
			[
				{
					"build" : ".",
					"jsonFile" : "directory-.-Debug-d0094a50bb2071803777.json",
					"minimumCMakeVersion" : 
					{
						"string" : "3.29"
					},
					"projectIndex" : 0,
					"source" : ".",
					"targetIndexes" : 
					[
						0
					]
				}
			],
			"name" : "Debug",
			"projects" : 
			[
				{
					"directoryIndexes" : 
					[
						0
					],
					"name" : "Dual_Board_COM_RX",
					"targetIndexes" : 
					[
						0
					]
				}
			],
			"targets" : 
			[
				{
					"directoryIndex" : 0,
					"id" : "Dual_Board_COM_RX.elf::@6890427a1f51a3e7e1df",
					"jsonFile" : "target-Dual_Board_COM_RX.elf-Debug-9c3fad1ff491a2e727f2.json",
					"name" : "Dual_Board_COM_RX.elf",
					"projectIndex" : 0
				}
			]
		}
	],
	"kind" : "codemodel",
	"paths" : 
	{
		"build" : "D:/STM32Project/Dual_Board_COM_RX/cmake-build-debug",
		"source" : "D:/STM32Project/Dual_Board_COM_RX"
	},
	"version" : 
	{
		"major" : 2,
		"minor" : 7
	}
}
